warp_tm_vis/__init__.py
warp_tm_vis/cli.py
warp_tm_vis/py.typed
warp_tm_vis/utils.py
warp_tm_vis-0.0.2.dist-info/METADATA
warp_tm_vis-0.0.2.dist-info/WHEEL
warp_tm_vis-0.0.2.dist-info/entry_points.txt
warp_tm_vis-0.0.2.dist-info/licenses/LICENSE
warp_tm_vis-0.0.2.dist-info/RECORD
