Metadata-Version: 2.4
Name: warp-tm-vis
Version: 0.0.2
Summary: Visualize template matching results from WarpTools
Project-URL: homepage, https://github.com/warpem/warp-tm-vis
Project-URL: repository, https://github.com/warpem/warp-tm-vis
Author-email: Alister Burt <burt.alister@gene.com>
License: BSD-3-Clause
License-File: LICENSE
Classifier: Development Status :: 3 - Alpha
Classifier: License :: OSI Approved :: BSD License
Classifier: Programming Language :: Python :: 3
Classifier: Programming Language :: Python :: 3.9
Classifier: Programming Language :: Python :: 3.10
Classifier: Programming Language :: Python :: 3.11
Classifier: Programming Language :: Python :: 3.12
Classifier: Programming Language :: Python :: 3.13
Classifier: Typing :: Typed
Requires-Python: >=3.11
Requires-Dist: mrcfile>=1.5.4
Requires-Dist: napari[pyqt5]>=0.5.6
Requires-Dist: numpy>=2.2.2
Requires-Dist: rich>=13.9.4
Requires-Dist: starfile>=0.5.11
Requires-Dist: typer>=0.15.1
Provides-Extra: dev
Requires-Dist: ipython; extra == 'dev'
Requires-Dist: mypy; extra == 'dev'
Requires-Dist: pdbpp; extra == 'dev'
Requires-Dist: pre-commit; extra == 'dev'
Requires-Dist: rich; extra == 'dev'
Requires-Dist: ruff; extra == 'dev'
Provides-Extra: test
Requires-Dist: pytest; extra == 'test'
Requires-Dist: pytest-cov; extra == 'test'
